{
    "id": "P112Q3B2_ASAP_SECURE_LIFE_ROBOTIZED_RECIPE",
    "status": "OK",
    "generated_at": "2026-06-08T16:46:44+00:00",
    "matrix_ok": true,
    "scenarios": [
        {
            "kind": "navigation",
            "method": "GET",
            "user": "guest",
            "label": "Invité",
            "language": "fr",
            "route_path": "/fr/public",
            "route_name": "public_fr",
            "expect_allowed": true,
            "expected_rights": "lecture publique uniquement",
            "request_path": "/asap-secure-life/fr/public",
            "request_method": "GET",
            "matched_route": "public_fr",
            "route_acl": "page_public:read",
            "route_fsm_guard": "ROUTE_PUBLIC",
            "observed_allowed": true,
            "passed": true,
            "reason": "SECURE_GATE_ALLOWED",
            "fsm_state": "PUBLIC_ALLOWED",
            "fsm_signal": "ROUTE_PUBLIC",
            "acl_role": "guest",
            "acl_resource": "page_public",
            "acl_privilege": "read",
            "metadata_source": "route"
        },
        {
            "kind": "navigation",
            "method": "GET",
            "user": "editor",
            "label": "Éditeur",
            "language": "es",
            "route_path": "/es/editor",
            "route_name": "editor_es",
            "expect_allowed": true,
            "expected_rights": "édition autorisée, administration refusée",
            "request_path": "/asap-secure-life/es/editor",
            "request_method": "GET",
            "matched_route": "editor_es",
            "route_acl": "page_editor:edit",
            "route_fsm_guard": "ROUTE_EDITOR",
            "observed_allowed": true,
            "passed": true,
            "reason": "SECURE_GATE_ALLOWED",
            "fsm_state": "EDITOR_ALLOWED",
            "fsm_signal": "ROUTE_EDITOR",
            "acl_role": "editor",
            "acl_resource": "page_editor",
            "acl_privilege": "edit",
            "metadata_source": "route"
        },
        {
            "kind": "navigation",
            "method": "GET",
            "user": "admin",
            "label": "Administrateur",
            "language": "en",
            "route_path": "/en/admin",
            "route_name": "admin_en",
            "expect_allowed": true,
            "expected_rights": "administration complète",
            "request_path": "/asap-secure-life/en/admin",
            "request_method": "GET",
            "matched_route": "admin_en",
            "route_acl": "page_admin:admin",
            "route_fsm_guard": "ROUTE_ADMIN",
            "observed_allowed": true,
            "passed": true,
            "reason": "SECURE_GATE_ALLOWED",
            "fsm_state": "ADMIN_ALLOWED",
            "fsm_signal": "ROUTE_ADMIN",
            "acl_role": "admin",
            "acl_resource": "page_admin",
            "acl_privilege": "admin",
            "metadata_source": "route"
        },
        {
            "kind": "navigation",
            "method": "GET",
            "user": "guest",
            "label": "Invité",
            "language": "fr",
            "route_path": "/en/admin",
            "route_name": "admin_en",
            "expect_allowed": false,
            "expected_rights": "administration refusée",
            "request_path": "/asap-secure-life/en/admin",
            "request_method": "GET",
            "matched_route": "admin_en",
            "route_acl": "page_admin:admin",
            "route_fsm_guard": "ROUTE_ADMIN",
            "observed_allowed": false,
            "passed": true,
            "reason": "ACL_ACCESS_DENIED: ACL_ACCESS_DENIED"
        },
        {
            "kind": "navigation",
            "method": "GET",
            "user": "editor",
            "label": "Éditeur",
            "language": "es",
            "route_path": "/en/admin",
            "route_name": "admin_en",
            "expect_allowed": false,
            "expected_rights": "administration refusée",
            "request_path": "/asap-secure-life/en/admin",
            "request_method": "GET",
            "matched_route": "admin_en",
            "route_acl": "page_admin:admin",
            "route_fsm_guard": "ROUTE_ADMIN",
            "observed_allowed": false,
            "passed": true,
            "reason": "ACL_ACCESS_DENIED: ACL_ACCESS_DENIED"
        },
        {
            "kind": "form",
            "method": "POST",
            "user": "guest",
            "label": "Invité",
            "language": "fr",
            "route_path": "/fr/contact",
            "route_name": "form_public_fr",
            "expect_allowed": true,
            "expected_rights": "formulaire public autorisé",
            "form_title": "Contact public",
            "form_field": "message",
            "form_value": "Bonjour ASAP",
            "request_path": "/asap-secure-life/fr/contact",
            "request_method": "POST",
            "matched_route": "form_public_fr",
            "route_acl": "public_form:submit",
            "route_fsm_guard": "FORM_GUEST_SUBMIT",
            "observed_allowed": true,
            "passed": true,
            "reason": "SECURE_GATE_ALLOWED",
            "fsm_state": "PUBLIC_FORM_SUBMITTED",
            "fsm_signal": "FORM_GUEST_SUBMIT",
            "acl_role": "guest",
            "acl_resource": "public_form",
            "acl_privilege": "submit",
            "metadata_source": "route"
        },
        {
            "kind": "form",
            "method": "POST",
            "user": "editor",
            "label": "Éditeur",
            "language": "es",
            "route_path": "/es/editor/form",
            "route_name": "form_editor_es",
            "expect_allowed": true,
            "expected_rights": "formulaire éditeur autorisé",
            "form_title": "Formulario editor",
            "form_field": "note",
            "form_value": "Edición segura",
            "request_path": "/asap-secure-life/es/editor/form",
            "request_method": "POST",
            "matched_route": "form_editor_es",
            "route_acl": "editor_form:submit",
            "route_fsm_guard": "FORM_EDITOR_SUBMIT",
            "observed_allowed": true,
            "passed": true,
            "reason": "SECURE_GATE_ALLOWED",
            "fsm_state": "EDITOR_FORM_SUBMITTED",
            "fsm_signal": "FORM_EDITOR_SUBMIT",
            "acl_role": "editor",
            "acl_resource": "editor_form",
            "acl_privilege": "submit",
            "metadata_source": "route"
        },
        {
            "kind": "form",
            "method": "POST",
            "user": "admin",
            "label": "Administrateur",
            "language": "en",
            "route_path": "/en/admin/settings",
            "route_name": "form_admin_en",
            "expect_allowed": true,
            "expected_rights": "formulaire admin autorisé",
            "form_title": "Admin settings",
            "form_field": "setting",
            "form_value": "secure-by-design",
            "request_path": "/asap-secure-life/en/admin/settings",
            "request_method": "POST",
            "matched_route": "form_admin_en",
            "route_acl": "admin_form:submit",
            "route_fsm_guard": "FORM_ADMIN_SUBMIT",
            "observed_allowed": true,
            "passed": true,
            "reason": "SECURE_GATE_ALLOWED",
            "fsm_state": "ADMIN_FORM_SUBMITTED",
            "fsm_signal": "FORM_ADMIN_SUBMIT",
            "acl_role": "admin",
            "acl_resource": "admin_form",
            "acl_privilege": "submit",
            "metadata_source": "route"
        },
        {
            "kind": "form",
            "method": "POST",
            "user": "guest",
            "label": "Invité",
            "language": "fr",
            "route_path": "/en/admin/settings",
            "route_name": "form_admin_en",
            "expect_allowed": false,
            "expected_rights": "formulaire admin refusé",
            "form_title": "Admin settings denied",
            "form_field": "setting",
            "form_value": "denied",
            "request_path": "/asap-secure-life/en/admin/settings",
            "request_method": "POST",
            "matched_route": "form_admin_en",
            "route_acl": "admin_form:submit",
            "route_fsm_guard": "FORM_ADMIN_SUBMIT",
            "observed_allowed": false,
            "passed": true,
            "reason": "ACL_ACCESS_DENIED: ACL_ACCESS_DENIED"
        },
        {
            "kind": "form",
            "method": "POST",
            "user": "editor",
            "label": "Éditeur",
            "language": "es",
            "route_path": "/en/admin/settings",
            "route_name": "form_admin_en",
            "expect_allowed": false,
            "expected_rights": "formulaire admin refusé",
            "form_title": "Admin settings denied",
            "form_field": "setting",
            "form_value": "denied",
            "request_path": "/asap-secure-life/en/admin/settings",
            "request_method": "POST",
            "matched_route": "form_admin_en",
            "route_acl": "admin_form:submit",
            "route_fsm_guard": "FORM_ADMIN_SUBMIT",
            "observed_allowed": false,
            "passed": true,
            "reason": "ACL_ACCESS_DENIED: ACL_ACCESS_DENIED"
        },
        {
            "kind": "form",
            "method": "GET",
            "user": "guest",
            "label": "Invité",
            "language": "fr",
            "route_path": "/fr/contact",
            "route_name": "form_public_fr",
            "expect_allowed": false,
            "expected_rights": "GET interdit sur formulaire POST",
            "form_title": "Contact public method denied",
            "form_field": "message",
            "form_value": "GET denied",
            "request_path": "/asap-secure-life/fr/contact",
            "request_method": "GET",
            "matched_route": null,
            "route_acl": null,
            "route_fsm_guard": null,
            "observed_allowed": false,
            "passed": true,
            "reason": "ASAP_ROUTE_METHOD_NOT_ALLOWED: GET /fr/contact allowed-routes=form_public_fr[POST]"
        }
    ],
    "mail": {
        "status": "DELIVERED_TO_MAILPIT",
        "reason": "SMTP_ACCEPTED_BY_LOCAL_MAILPIT",
        "required": true,
        "mode": "smtp",
        "host": "127.0.0.1",
        "port": 1025,
        "to": "philstephibanez@gamil.com",
        "from": "asap-recipes@localhost",
        "smtp_data_response": "250 2.0.0 Ok: queued as 2YAXATL2T0qG5tterpNSa5"
    },
    "panther": {
        "status": "SKIPPED",
        "reason": "PANTHER_CLIENT_NOT_AVAILABLE",
        "required": false,
        "autoload_path": "H:\\/ASAP_REF_BOOK/vendor/autoload.php",
        "autoload_tried": [
            "H:\\ASAP/vendor/autoload.php",
            "H:\\ASAP/tools/vendor/autoload.php",
            "H:\\/ASAP_REF_BOOK/vendor/autoload.php"
        ]
    },
    "reports": {
        "json": "H:\\ASAP/var/reports/p112q3b2/p112q3b2_secure_life_robotized_recipe.json",
        "markdown": "H:\\ASAP/var/reports/p112q3b2/p112q3b2_secure_life_robotized_recipe.md",
        "html": "H:\\ASAP/var/reports/p112q3b2/p112q3b2_secure_life_robotized_recipe.html",
        "email_html": "H:\\ASAP/var/reports/p112q3b2/p112q3b2_secure_life_robotized_recipe_email.html",
        "eml": "H:\\ASAP/var/reports/p112q3b2/p112q3b2_secure_life_robotized_recipe.eml",
        "panther_screenshot": null
    }
}