{
  "patch_id": "P4J_MOVE_LEGACY_ROOT_CLASSES",
  "contract": {
    "wrapper_is_fallback": true,
    "no_wrapper": true,
    "no_silent_fallback": true,
    "no_runtime_direct_legacy_path_reference": true,
    "autoload_is_the_only_legacy_symbol_resolution_path": true
  },
  "non_runtime_reference_roots": [
    "DOC/",
    "tools/audits/",
    "tools/migrations/",
    "tools/smokes/",
    "RUN_P4J_MOVE_LEGACY_ROOT_CLASSES.cmd"
  ],
  "content_replacements": [
    {
      "path": "Opus/Singleton.class.php",
      "reason": "Remove direct legacy file include. OPUS_AccessorInterface must be resolved by autoload after both classes are moved out of framework root.",
      "search": "require_once __DIR__ . '/AccessorInterface.class.php';\n\n",
      "replace": ""
    }
  ],
  "moves": [
    {
      "symbol": "OPUS_AccessorInterface",
      "kind": "interface",
      "source": "Opus/AccessorInterface.class.php",
      "target": "Opus/Accessor/AccessorInterface.class.php"
    },
    {
      "symbol": "OPUS_ConfigLoader",
      "kind": "class",
      "source": "Opus/ConfigLoader.class.php",
      "target": "Opus/Config/ConfigLoader.class.php"
    },
    {
      "symbol": "OPUS_Configuration",
      "kind": "class",
      "source": "Opus/Configuration.class.php",
      "target": "Opus/Config/Configuration.class.php"
    },
    {
      "symbol": "OPUS_Debug",
      "kind": "class",
      "source": "Opus/Debug.class.php",
      "target": "Opus/Debug/Debug.class.php"
    },
    {
      "symbol": "OPUS_Exception",
      "kind": "class",
      "source": "Opus/Exception.class.php",
      "target": "Opus/Exception/Exception.class.php"
    },
    {
      "symbol": "OPUS_SimpleXMLElementExtended",
      "kind": "class",
      "source": "Opus/SimpleXMLElementExtended.class.php",
      "target": "Opus/Xml/SimpleXMLElementExtended.class.php"
    },
    {
      "symbol": "OPUS_Singleton",
      "kind": "class",
      "source": "Opus/Singleton.class.php",
      "target": "Opus/Core/Singleton.class.php"
    }
  ]
}
